{
  "/_not-found/page": "app/_not-found/page.js",
  "/apple-icon.png/route": "app/apple-icon.png/route.js",
  "/icon.png/route": "app/icon.png/route.js",
  "/api/activity-file/[id]/route": "app/api/activity-file/[id]/route.js",
  "/api/download/macos/route": "app/api/download/macos/route.js",
  "/api/activity-file/route": "app/api/activity-file/route.js",
  "/api/federation/heartbeat/route": "app/api/federation/heartbeat/route.js",
  "/api/federation/v1/[scope]/route": "app/api/federation/v1/[scope]/route.js",
  "/api/health/route": "app/api/health/route.js",
  "/api/export/route": "app/api/export/route.js",
  "/api/federation/v1/image/[id]/route": "app/api/federation/v1/image/[id]/route.js",
  "/api/social/new/route": "app/api/social/new/route.js",
  "/api/social/image/route": "app/api/social/image/route.js",
  "/api/import/route": "app/api/import/route.js",
  "/api/social/thread/route": "app/api/social/thread/route.js",
  "/api/sync/route": "app/api/sync/route.js",
  "/api/workout/fit/route": "app/api/workout/fit/route.js",
  "/calendar.ics/route": "app/calendar.ics/route.js",
  "/privacy/page": "app/privacy/page.js",
  "/login/page": "app/login/page.js",
  "/(app)/atp/page": "app/(app)/atp/page.js",
  "/(app)/workout-comparison/page": "app/(app)/workout-comparison/page.js",
  "/(app)/dashboard/page": "app/(app)/dashboard/page.js",
  "/(app)/import/page": "app/(app)/import/page.js",
  "/(app)/peaks/page": "app/(app)/peaks/page.js",
  "/(app)/activity/[id]/page": "app/(app)/activity/[id]/page.js",
  "/(app)/routes/page": "app/(app)/routes/page.js",
  "/(app)/calendar/page": "app/(app)/calendar/page.js",
  "/(app)/settings/page": "app/(app)/settings/page.js",
  "/(app)/social/page": "app/(app)/social/page.js",
  "/(app)/metrics/page": "app/(app)/metrics/page.js",
  "/(app)/progression/page": "app/(app)/progression/page.js",
  "/(app)/strength/page": "app/(app)/strength/page.js",
  "/(app)/page": "app/(app)/page.js",
  "/(app)/workout-library/new/page": "app/(app)/workout-library/new/page.js",
  "/(app)/workout-library/[id]/page": "app/(app)/workout-library/[id]/page.js",
  "/(app)/workout-library/page": "app/(app)/workout-library/page.js"
}